{"cached_at": "2025-04-24T17:54:53.425307", "value": {"id": 92782, "name": "Ms. Marvel", "original_name": "Ms. Marvel", "overview": "A great student, avid gamer, and voracious fan-fic scribe, Kamala Khan has a special affinity for superheroes, particularly Captain Marvel. However, she struggles to fit in at home and at school \u2014 that is, until she gets superpowers like the heroes she\u2019s always looked up to. Life is easier with superpowers, right?", "first_air_date": "2022-06-08", "genre_ids": [], "popularity": 7.6045, "vote_average": 6.359, "vote_count": 1268, "genres": [{"id": 10765, "name": "Sci-Fi & Fantasy"}, {"id": 10759, "name": "Action & Adventure"}, {"id": 35, "name": "Comedy"}], "networks": [{"id": 2739, "name": "Disney+"}], "status": "Ended", "type": "Miniseries", "number_of_seasons": 1, "number_of_episodes": 6, "in_production": false, "languages": ["en"], "last_air_date": "2022-07-13", "seasons": [{"id": 130652, "name": "Miniseries", "season_number": 1, "episode_count": 6, "air_date": "2022-06-08", "overview": "A great student, avid gamer, and voracious fan-fic scribe, Kamala Khan has a special affinity for superheroes, particularly Captain Marvel. However, she struggles to fit in at home and at school \u2014 that is, until she gets superpowers like the heroes she\u2019s always looked up to. Life is easier with superpowers, right?", "episodes": []}], "air_date": null, "episodes": []}}